onlykey/__init__.py
onlykey/cli.py
onlykey/client.py
onlykey-1.2.0.dist-info/METADATA
onlykey-1.2.0.dist-info/WHEEL
onlykey-1.2.0.dist-info/entry_points.txt
onlykey-1.2.0.dist-info/top_level.txt
onlykey-1.2.0.dist-info/RECORD
